navcom/__init__.py
navcom/cli.py
navcom_py-1.0.0.dist-info/METADATA
navcom_py-1.0.0.dist-info/WHEEL
navcom_py-1.0.0.dist-info/entry_points.txt
navcom_py-1.0.0.dist-info/top_level.txt
navcom_py-1.0.0.dist-info/RECORD
