Metadata-Version: 2.4
Name: navcom-py
Version: 1.0.0
Summary: Navigate through git repository commits chronologically
Author: Gaura
Requires-Python: >=3.7
Requires-Dist: click>=8.3.0
Dynamic: author
Dynamic: requires-python
